superconf/__init__.py
superconf/anchors.py
superconf/casts.py
superconf/common.py
superconf/common_beta.py
superconf/configuration.py
superconf/exceptions.py
superconf/fields.py
superconf/loaders.py
superconf/parsers.py
superconf/wrapper.py
superconf-0.1.3.dist-info/LICENSE.txt
superconf-0.1.3.dist-info/METADATA
superconf-0.1.3.dist-info/WHEEL
superconf-0.1.3.dist-info/entry_points.txt
superconf-0.1.3.dist-info/RECORD
