Metadata-Version: 2.1
Name: superconf
Version: 0.1.3
Summary: Super config for python
License: GPLv3
Author: mrjk
Author-email: mrjk.78@gmail.com
Requires-Python: >=3.9,<4.0
Classifier: License :: Other/Proprietary License
Classifier: Programming Language :: Python :: 3
Classifier: Programming Language :: Python :: 3.9
Classifier: Programming Language :: Python :: 3.10
Classifier: Programming Language :: Python :: 3.11
Classifier: Programming Language :: Python :: 3.12
Classifier: Programming Language :: Python :: 3.13
Requires-Dist: pyaml (>=24.12.1,<25.0.0)
